Workbook

Sheet Inputs
A1: Crypto Plan 2027–2028 — Inputs
A2: Blue text = inputs you can change. Yellow = key assumptions. Black = formulas. Prices from Binance (USDT pairs), 8 Oct 2026.
A3: Total budget (₹) | B3: 100000 | C3: Your total investment.
A4: USD → INR rate | B4: 96.8 | C4: open.er-api.com, 8 Oct 2026. Indian exchanges often quote INR a few % higher.
A5: Share for monthly buys | B5: 0.6 | C5: Spent in equal parts over the buy months.
A6: Share for Dip order 1 | B6: 0.2 | C6: Limit order near the 90-day low.
A7: Share for Dip order 2 | B7: =1-B5-B6 -> 0.2 | C7: Remainder; limit order near the 2026 low.
A8: Number of monthly buys | B8: 12 | C8: Jan–Dec 2027.
A9: Tax on crypto gains | B9: 0.312 | C9: 30% + 4% cess (India, Sec 115BBH). Losses cannot be set off.
A10: TDS on each sale | B10: 0.01 | C10: 1% TDS (Sec 194S), adjustable when filing.
A13: Coin | B13: Allocation % | C13: Amount (₹) | D13: Price 8-Oct-2026 ($) | E13: Price 8-Oct-2026 (₹) | F13: 2026 low ($) | G13: High since 2023 ($) | H13: Today vs high | I13: Role
A14: BTC | B14: 0.45 | C14: =$B$3*B14 -> 45000 | D14: 80710 | E14: =D14*$B$4 -> 7812728 | F14: 58620 | G14: 124660 | H14: =IFERROR(D14/G14-1,0) -> -0.35255896 | I14: Core holding, most reliable
A15: ETH | B15: 0.15 | C15: =$B$3*B15 -> 15000 | D15: 2418 | E15: =D15*$B$4 -> 234062.4 | F15: 1568 | G15: 4832 | H15: =IFERROR(D15/G15-1,0) -> -0.49958609 | I15: Second-largest coin
A16: SOL | B16: 0.15 | C16: =$B$3*B16 -> 15000 | D16: 106.5 | E16: =D16*$B$4 -> 10309.2 | F16: 62.2 | G16: 262 | H16: =IFERROR(D16/G16-1,0) -> -0.59351145 | I16: Biggest gainer in last recovery
A17: BNB | B17: 0.1 | C17: =$B$3*B17 -> 10000 | D17: 722.4 | E17: =D17*$B$4 -> 69928.32 | F17: 546.5 | G17: 1307 | H17: =IFERROR(D17/G17-1,0) -> -0.44728386 | I17: Steady performer
A18: TRX | B18: 0.05 | C18: =$B$3*B18 -> 5000 | D18: 0.333 | E18: =D18*$B$4 -> 32.2344 | F18: 0.2696 | G18: 0.4334 | H18: =IFERROR(D18/G18-1,0) -> -0.23165667 | I18: Profit in 90% of past 2-yr periods
A19: INJ | B19: 0.05 | C19: =$B$3*B19 -> 5000 | D19: 6.512 | E19: =D19*$B$4 -> 630.3616 | F19: 2.745 | G19: 51.85 | H19: =IFERROR(D19/G19-1,0) -> -0.87440694 | I19: High risk / high reward
A20: DOGE | B20: 0.05 | C20: =$B$3*B20 -> 5000 | D20: 0.08149 | E20: =D20*$B$4 -> 7.888232 | F20: 0.06909 | G20: 0.4663 | H20: =IFERROR(D20/G20-1,0) -> -0.82524126 | I20: Meme coin, high risk
A21: Total | B21: =SUM(B14:B20) -> 1 | C21: =SUM(C14:C20) -> 100000
A22: Allocation must total 100%: | B22: =IF(ROUND(B21,4)=1,"OK","Check: not 100%") -> OK
A24: Source: Binance public market data (data-api.binance.vision), daily closes to 8 Oct 2026. High = highest daily close since Jan 2023.

Sheet Buy Plan
A1: Buy Plan — how much to buy, and at which price
A2: Monthly buy on the 1st of each month in 2027. Dip orders = limit orders; if not filled by Jul 2028, buy at market that month.
A4: Coin | B4: Total for coin (₹) | C4: Monthly buy (₹) | D4: Dip 1 price ($) | E4: Dip 1 price (₹) | F4: Dip 1 amount (₹) | G4: Dip 1 vs today | H4: Dip 2 price ($) | I4: Dip 2 price (₹) | J4: Dip 2 amount (₹) | K4: Dip 2 vs today | L4: Check total (₹)
A5: =Inputs!A14 -> BTC | B5: =Inputs!C14 -> 45000 | C5: =B5*Inputs!$B$5/Inputs!$B$8 -> 2250 | D5: 65000 | E5: =D5*Inputs!$B$4 -> 6292000 | F5: =B5*Inputs!$B$6 -> 9000 | G5: =IFERROR(D5/Inputs!D14-1,0) -> -0.1946475 | H5: 58000 | I5: =H5*Inputs!$B$4 -> 5614400 | J5: =B5*Inputs!$B$7 -> 9000 | K5: =IFERROR(H5/Inputs!D14-1,0) -> -0.28137777 | L5: =C5*Inputs!$B$8+F5+J5 -> 45000
A6: =Inputs!A15 -> ETH | B6: =Inputs!C15 -> 15000 | C6: =B6*Inputs!$B$5/Inputs!$B$8 -> 750 | D6: 1850 | E6: =D6*Inputs!$B$4 -> 179080 | F6: =B6*Inputs!$B$6 -> 3000 | G6: =IFERROR(D6/Inputs!D15-1,0) -> -0.23490488 | H6: 1600 | I6: =H6*Inputs!$B$4 -> 154880 | J6: =B6*Inputs!$B$7 -> 3000 | K6: =IFERROR(H6/Inputs!D15-1,0) -> -0.33829611 | L6: =C6*Inputs!$B$8+F6+J6 -> 15000
A7: =Inputs!A16 -> SOL | B7: =Inputs!C16 -> 15000 | C7: =B7*Inputs!$B$5/Inputs!$B$8 -> 750 | D7: 78 | E7: =D7*Inputs!$B$4 -> 7550.4 | F7: =B7*Inputs!$B$6 -> 3000 | G7: =IFERROR(D7/Inputs!D16-1,0) -> -0.26760563 | H7: 63 | I7: =H7*Inputs!$B$4 -> 6098.4 | J7: =B7*Inputs!$B$7 -> 3000 | K7: =IFERROR(H7/Inputs!D16-1,0) -> -0.4084507 | L7: =C7*Inputs!$B$8+F7+J7 -> 15000
A8: =Inputs!A17 -> BNB | B8: =Inputs!C17 -> 10000 | C8: =B8*Inputs!$B$5/Inputs!$B$8 -> 500 | D8: 600 | E8: =D8*Inputs!$B$4 -> 58080 | F8: =B8*Inputs!$B$6 -> 2000 | G8: =IFERROR(D8/Inputs!D17-1,0) -> -0.16943522 | H8: 550 | I8: =H8*Inputs!$B$4 -> 53240 | J8: =B8*Inputs!$B$7 -> 2000 | K8: =IFERROR(H8/Inputs!D17-1,0) -> -0.23864895 | L8: =C8*Inputs!$B$8+F8+J8 -> 10000
A9: =Inputs!A18 -> TRX | B9: =Inputs!C18 -> 5000 | C9: =B9*Inputs!$B$5/Inputs!$B$8 -> 250 | D9: 0.29 | E9: =D9*Inputs!$B$4 -> 28.072 | F9: =B9*Inputs!$B$6 -> 1000 | G9: =IFERROR(D9/Inputs!D18-1,0) -> -0.12912913 | H9: 0.27 | I9: =H9*Inputs!$B$4 -> 26.136 | J9: =B9*Inputs!$B$7 -> 1000 | K9: =IFERROR(H9/Inputs!D18-1,0) -> -0.18918919 | L9: =C9*Inputs!$B$8+F9+J9 -> 5000
A10: =Inputs!A19 -> INJ | B10: =Inputs!C19 -> 5000 | C10: =B10*Inputs!$B$5/Inputs!$B$8 -> 250 | D10: 4.2 | E10: =D10*Inputs!$B$4 -> 406.56 | F10: =B10*Inputs!$B$6 -> 1000 | G10: =IFERROR(D10/Inputs!D19-1,0) -> -0.35503686 | H10: 3 | I10: =H10*Inputs!$B$4 -> 290.4 | J10: =B10*Inputs!$B$7 -> 1000 | K10: =IFERROR(H10/Inputs!D19-1,0) -> -0.53931204 | L10: =C10*Inputs!$B$8+F10+J10 -> 5000
A11: =Inputs!A20 -> DOGE | B11: =Inputs!C20 -> 5000 | C11: =B11*Inputs!$B$5/Inputs!$B$8 -> 250 | D11: 0.07 | E11: =D11*Inputs!$B$4 -> 6.776 | F11: =B11*Inputs!$B$6 -> 1000 | G11: =IFERROR(D11/Inputs!D20-1,0) -> -0.1409989 | H11: 0.06 | I11: =H11*Inputs!$B$4 -> 5.808 | J11: =B11*Inputs!$B$7 -> 1000 | K11: =IFERROR(H11/Inputs!D20-1,0) -> -0.26371334 | L11: =C11*Inputs!$B$8+F11+J11 -> 5000
A12: Total | B12: =SUM(B5:B11) -> 100000 | C12: =SUM(C5:C11) -> 5000 | F12: =SUM(F5:F11) -> 20000 | J12: =SUM(J5:J11) -> 20000 | L12: =SUM(L5:L11) -> 100000
A14: How the dip prices were chosen: Dip 1 ≈ the low of the last 90 days; Dip 2 ≈ the 2026 low (e.g. BTC $58.6k on 30 Jun 2026).
A15: Past cycles fell in July 2027 and July 2028 (by analogy), so watch those months for dip orders to fill.
A16: Safety rule: if BTC closes a week below $58,600, keep monthly buys but don't add dip money until it climbs back above.
A17: Indian exchanges quote INR prices: compare the USD price on the exchange's USDT market, or adjust the ₹ levels for the exchange premium.

Sheet Monthly Schedule
A1: Month-by-month plan, Jan 2027 – Dec 2028
A2: Buy amounts update from 'Buy Plan'. 'Past cycles' = BTC's average return in the matching month of the 2017–21 and 2021–25 cycles (guide only).
A4: Month | B4: Past cycles (BTC avg) | C4: Monthly buy? (1=yes) | D4: BTC buy (₹) | E4: ETH buy (₹) | F4: SOL buy (₹) | G4: BNB buy (₹) | H4: TRX buy (₹) | I4: INJ buy (₹) | J4: DOGE buy (₹) | K4: Total buy (₹) | L4: Cumulative bought (₹) | M4: Sell % of holdings | N4: Action | O4: Done? (✓)
A5: Jan 2027 | B5: 0.04 | C5: 1 | D5: =$C5*'Buy Plan'!$C$5 -> 2250 | E5: =$C5*'Buy Plan'!$C$6 -> 750 | F5: =$C5*'Buy Plan'!$C$7 -> 750 | G5: =$C5*'Buy Plan'!$C$8 -> 500 | H5: =$C5*'Buy Plan'!$C$9 -> 250 | I5: =$C5*'Buy Plan'!$C$10 -> 250 | J5: =$C5*'Buy Plan'!$C$11 -> 250 | K5: =SUM(D5:J5) -> 5000 | L5: =K5 -> 5000 | M5: 0 | N5: Monthly buy. Place Dip 1 and Dip 2 limit orders for every coin.
A6: Feb 2027 | B6: 0.26 | C6: 1 | D6: =$C6*'Buy Plan'!$C$5 -> 2250 | E6: =$C6*'Buy Plan'!$C$6 -> 750 | F6: =$C6*'Buy Plan'!$C$7 -> 750 | G6: =$C6*'Buy Plan'!$C$8 -> 500 | H6: =$C6*'Buy Plan'!$C$9 -> 250 | I6: =$C6*'Buy Plan'!$C$10 -> 250 | J6: =$C6*'Buy Plan'!$C$11 -> 250 | K6: =SUM(D6:J6) -> 5000 | L6: =L5+K6 -> 10000 | M6: 0 | N6: Monthly buy.
A7: Mar 2027 | B7: 0.32 | C7: 1 | D7: =$C7*'Buy Plan'!$C$5 -> 2250 | E7: =$C7*'Buy Plan'!$C$6 -> 750 | F7: =$C7*'Buy Plan'!$C$7 -> 750 | G7: =$C7*'Buy Plan'!$C$8 -> 500 | H7: =$C7*'Buy Plan'!$C$9 -> 250 | I7: =$C7*'Buy Plan'!$C$10 -> 250 | J7: =$C7*'Buy Plan'!$C$11 -> 250 | K7: =SUM(D7:J7) -> 5000 | L7: =L6+K7 -> 15000 | M7: 0 | N7: Monthly buy (prices often jump here — don't chase).
A8: Apr 2027 | B8: 0.1 | C8: 1 | D8: =$C8*'Buy Plan'!$C$5 -> 2250 | E8: =$C8*'Buy Plan'!$C$6 -> 750 | F8: =$C8*'Buy Plan'!$C$7 -> 750 | G8: =$C8*'Buy Plan'!$C$8 -> 500 | H8: =$C8*'Buy Plan'!$C$9 -> 250 | I8: =$C8*'Buy Plan'!$C$10 -> 250 | J8: =$C8*'Buy Plan'!$C$11 -> 250 | K8: =SUM(D8:J8) -> 5000 | L8: =L7+K8 -> 20000 | M8: 0 | N8: Monthly buy.
A9: May 2027 | B9: 0.02 | C9: 1 | D9: =$C9*'Buy Plan'!$C$5 -> 2250 | E9: =$C9*'Buy Plan'!$C$6 -> 750 | F9: =$C9*'Buy Plan'!$C$7 -> 750 | G9: =$C9*'Buy Plan'!$C$8 -> 500 | H9: =$C9*'Buy Plan'!$C$9 -> 250 | I9: =$C9*'Buy Plan'!$C$10 -> 250 | J9: =$C9*'Buy Plan'!$C$11 -> 250 | K9: =SUM(D9:J9) -> 5000 | L9: =L8+K9 -> 25000 | M9: 0 | N9: Monthly buy.
A10: Jun 2027 | B10: -0.04 | C10: 1 | D10: =$C10*'Buy Plan'!$C$5 -> 2250 | E10: =$C10*'Buy Plan'!$C$6 -> 750 | F10: =$C10*'Buy Plan'!$C$7 -> 750 | G10: =$C10*'Buy Plan'!$C$8 -> 500 | H10: =$C10*'Buy Plan'!$C$9 -> 250 | I10: =$C10*'Buy Plan'!$C$10 -> 250 | J10: =$C10*'Buy Plan'!$C$11 -> 250 | K10: =SUM(D10:J10) -> 5000 | L10: =L9+K10 -> 30000 | M10: 0 | N10: Monthly buy. Watch for dip orders to fill.
A11: Jul 2027 | B11: -0.12 | C11: 1 | D11: =$C11*'Buy Plan'!$C$5 -> 2250 | E11: =$C11*'Buy Plan'!$C$6 -> 750 | F11: =$C11*'Buy Plan'!$C$7 -> 750 | G11: =$C11*'Buy Plan'!$C$8 -> 500 | H11: =$C11*'Buy Plan'!$C$9 -> 250 | I11: =$C11*'Buy Plan'!$C$10 -> 250 | J11: =$C11*'Buy Plan'!$C$11 -> 250 | K11: =SUM(D11:J11) -> 5000 | L11: =L10+K11 -> 35000 | M11: 0 | N11: Monthly buy. Best month to buy in this pattern (fell in both cycles).
A12: Aug 2027 | B12: 0.07 | C12: 1 | D12: =$C12*'Buy Plan'!$C$5 -> 2250 | E12: =$C12*'Buy Plan'!$C$6 -> 750 | F12: =$C12*'Buy Plan'!$C$7 -> 750 | G12: =$C12*'Buy Plan'!$C$8 -> 500 | H12: =$C12*'Buy Plan'!$C$9 -> 250 | I12: =$C12*'Buy Plan'!$C$10 -> 250 | J12: =$C12*'Buy Plan'!$C$11 -> 250 | K12: =SUM(D12:J12) -> 5000 | L12: =L11+K12 -> 40000 | M12: 0 | N12: Monthly buy.
A13: Sep 2027 | B13: 0.05 | C13: 1 | D13: =$C13*'Buy Plan'!$C$5 -> 2250 | E13: =$C13*'Buy Plan'!$C$6 -> 750 | F13: =$C13*'Buy Plan'!$C$7 -> 750 | G13: =$C13*'Buy Plan'!$C$8 -> 500 | H13: =$C13*'Buy Plan'!$C$9 -> 250 | I13: =$C13*'Buy Plan'!$C$10 -> 250 | J13: =$C13*'Buy Plan'!$C$11 -> 250 | K13: =SUM(D13:J13) -> 5000 | L13: =L12+K13 -> 45000 | M13: 0 | N13: Monthly buy.
A14: Oct 2027 | B14: 0.02 | C14: 1 | D14: =$C14*'Buy Plan'!$C$5 -> 2250 | E14: =$C14*'Buy Plan'!$C$6 -> 750 | F14: =$C14*'Buy Plan'!$C$7 -> 750 | G14: =$C14*'Buy Plan'!$C$8 -> 500 | H14: =$C14*'Buy Plan'!$C$9 -> 250 | I14: =$C14*'Buy Plan'!$C$10 -> 250 | J14: =$C14*'Buy Plan'!$C$11 -> 250 | K14: =SUM(D14:J14) -> 5000 | L14: =L13+K14 -> 50000 | M14: 0 | N14: Monthly buy.
A15: Nov 2027 | B15: 0.21 | C15: 1 | D15: =$C15*'Buy Plan'!$C$5 -> 2250 | E15: =$C15*'Buy Plan'!$C$6 -> 750 | F15: =$C15*'Buy Plan'!$C$7 -> 750 | G15: =$C15*'Buy Plan'!$C$8 -> 500 | H15: =$C15*'Buy Plan'!$C$9 -> 250 | I15: =$C15*'Buy Plan'!$C$10 -> 250 | J15: =$C15*'Buy Plan'!$C$11 -> 250 | K15: =SUM(D15:J15) -> 5000 | L15: =L14+K15 -> 55000 | M15: 0 | N15: Monthly buy (often a strong month).
A16: Dec 2027 | B16: -0.04 | C16: 1 | D16: =$C16*'Buy Plan'!$C$5 -> 2250 | E16: =$C16*'Buy Plan'!$C$6 -> 750 | F16: =$C16*'Buy Plan'!$C$7 -> 750 | G16: =$C16*'Buy Plan'!$C$8 -> 500 | H16: =$C16*'Buy Plan'!$C$9 -> 250 | I16: =$C16*'Buy Plan'!$C$10 -> 250 | J16: =$C16*'Buy Plan'!$C$11 -> 250 | K16: =SUM(D16:J16) -> 5000 | L16: =L15+K16 -> 60000 | M16: 0 | N16: Last monthly buy. Check dip orders are still open.
A17: Jan 2028 | B17: 0.09 | C17: 0 | D17: =$C17*'Buy Plan'!$C$5 -> 0 | E17: =$C17*'Buy Plan'!$C$6 -> 0 | F17: =$C17*'Buy Plan'!$C$7 -> 0 | G17: =$C17*'Buy Plan'!$C$8 -> 0 | H17: =$C17*'Buy Plan'!$C$9 -> 0 | I17: =$C17*'Buy Plan'!$C$10 -> 0 | J17: =$C17*'Buy Plan'!$C$11 -> 0 | K17: =SUM(D17:J17) -> 0 | L17: =L16+K17 -> 60000 | M17: 0 | N17: No monthly buy. Keep dip orders open.
... A28: Dec 2028 | B28: 0.23 | C28: 0 | D28: =$C28*'Buy Plan'!$C$5 -> 0 | E28: =$C28*'Buy Plan'!$C$6 -> 0 | F28: =$C28*'Buy Plan'!$C$7 -> 0 | G28: =$C28*'Buy Plan'!$C$8 -> 0 | H28: =$C28*'Buy Plan'!$C$9 -> 0 | I28: =$C28*'Buy Plan'!$C$10 -> 0 | J28: =$C28*'Buy Plan'!$C$11 -> 0 | K28: =SUM(D28:J28) -> 0 | L28: =L27+K28 -> 60000 | M28: 0.15 | N28: Sell 15%. Keep ~40% for the expected 2029 peak (trailing exit).
A29: Total | D29: =SUM(D5:D28) -> 27000 | E29: =SUM(E5:E28) -> 9000 | F29: =SUM(F5:F28) -> 9000 | G29: =SUM(G5:G28) -> 6000 | H29: =SUM(H5:H28) -> 3000 | I29: =SUM(I5:I28) -> 3000 | J29: =SUM(J5:J28) -> 3000 | K29: =SUM(K5:K28) -> 60000 | M29: =SUM(M5:M28) -> 0.6
A31: Monthly buys total ₹ = 'Monthly buy' share of budget. Dip orders (the other 40%) fill whenever price reaches the levels in 'Buy Plan' — log them in 'Tracker'.
A32: Sell % = calendar fallback. If a price target in 'Sell Plan' hits first, sell by target instead. Sell by calendar only if the coin is above your average buy price.
A33: Past-cycle source: Binance BTCUSDT monthly candles; month k after the Oct 2025 top matched to month k after the Dec 2017 and Nov 2021 tops.

Sheet Sell Plan
A1: Sell Plan — profit targets per coin
A2: Sell 20% of that coin's holding at each target. Keep the last 40% and exit when price falls the trailing % from its highest price.
A4: Coin | B4: Today ($) | C4: Target 1 ($) | D4: Target 1 (₹) | E4: T1 vs today | F4: Target 2 ($) | G4: Target 2 (₹) | H4: T2 vs today | I4: Target 3 ($) | J4: Target 3 (₹) | K4: T3 vs today | L4: Sell % at each target | M4: Trailing exit on last 40% | N4: Trailing exit price if high = T3 ($)
A5: =Inputs!A14 -> BTC | B5: =Inputs!D14 -> 80710 | C5: 110000 | D5: =C5*Inputs!$B$4 -> 10648000 | E5: =IFERROR(C5/B5,0) -> 1.3629042 | F5: 130000 | G5: =F5*Inputs!$B$4 -> 12584000 | H5: =IFERROR(F5/B5,0) -> 1.610705 | I5: 160000 | J5: =I5*Inputs!$B$4 -> 15488000 | K5: =IFERROR(I5/B5,0) -> 1.9824061 | L5: 0.2 | M5: 0.3 | N5: =I5*(1-M5) -> 112000
A6: =Inputs!A15 -> ETH | B6: =Inputs!D15 -> 2418 | C6: 3800 | D6: =C6*Inputs!$B$4 -> 367840 | E6: =IFERROR(C6/B6,0) -> 1.5715467 | F6: 4800 | G6: =F6*Inputs!$B$4 -> 464640 | H6: =IFERROR(F6/B6,0) -> 1.9851117 | I6: 6000 | J6: =I6*Inputs!$B$4 -> 580800 | K6: =IFERROR(I6/B6,0) -> 2.4813896 | L6: 0.2 | M6: 0.3 | N6: =I6*(1-M6) -> 4200
A7: =Inputs!A16 -> SOL | B7: =Inputs!D16 -> 106.5 | C7: 180 | D7: =C7*Inputs!$B$4 -> 17424 | E7: =IFERROR(C7/B7,0) -> 1.6901408 | F7: 250 | G7: =F7*Inputs!$B$4 -> 24200 | H7: =IFERROR(F7/B7,0) -> 2.3474178 | I7: 320 | J7: =I7*Inputs!$B$4 -> 30976 | K7: =IFERROR(I7/B7,0) -> 3.0046948 | L7: 0.2 | M7: 0.3 | N7: =I7*(1-M7) -> 224
A8: =Inputs!A17 -> BNB | B8: =Inputs!D17 -> 722.4 | C8: 1000 | D8: =C8*Inputs!$B$4 -> 96800 | E8: =IFERROR(C8/B8,0) -> 1.3842746 | F8: 1300 | G8: =F8*Inputs!$B$4 -> 125840 | H8: =IFERROR(F8/B8,0) -> 1.799557 | I8: 1600 | J8: =I8*Inputs!$B$4 -> 154880 | K8: =IFERROR(I8/B8,0) -> 2.2148394 | L8: 0.2 | M8: 0.3 | N8: =I8*(1-M8) -> 1120
A9: =Inputs!A18 -> TRX | B9: =Inputs!D18 -> 0.333 | C9: 0.42 | D9: =C9*Inputs!$B$4 -> 40.656 | E9: =IFERROR(C9/B9,0) -> 1.2612613 | F9: 0.5 | G9: =F9*Inputs!$B$4 -> 48.4 | H9: =IFERROR(F9/B9,0) -> 1.5015015 | I9: 0.6 | J9: =I9*Inputs!$B$4 -> 58.08 | K9: =IFERROR(I9/B9,0) -> 1.8018018 | L9: 0.2 | M9: 0.3 | N9: =I9*(1-M9) -> 0.42
A10: =Inputs!A19 -> INJ | B10: =Inputs!D19 -> 6.512 | C10: 15 | D10: =C10*Inputs!$B$4 -> 1452 | E10: =IFERROR(C10/B10,0) -> 2.3034398 | F10: 25 | G10: =F10*Inputs!$B$4 -> 2420 | H10: =IFERROR(F10/B10,0) -> 3.8390663 | I10: 40 | J10: =I10*Inputs!$B$4 -> 3872 | K10: =IFERROR(I10/B10,0) -> 6.1425061 | L10: 0.2 | M10: 0.4 | N10: =I10*(1-M10) -> 24
A11: =Inputs!A20 -> DOGE | B11: =Inputs!D20 -> 0.08149 | C11: 0.18 | D11: =C11*Inputs!$B$4 -> 17.424 | E11: =IFERROR(C11/B11,0) -> 2.20886 | F11: 0.3 | G11: =F11*Inputs!$B$4 -> 29.04 | H11: =IFERROR(F11/B11,0) -> 3.6814333 | I11: 0.45 | J11: =I11*Inputs!$B$4 -> 43.56 | K11: =IFERROR(I11/B11,0) -> 5.52215 | L11: 0.2 | M11: 0.4 | N11: =I11*(1-M11) -> 0.27
A13: How the targets were chosen: T1 ≈ a level the coin traded at in 2025; T2 ≈ the old all-time high; T3 = a modest new high (each cycle's gains have been smaller).
A14: Price rules that override the calendar: (1) if BTC reaches 2x your average buy price early, take out your original investment; (2) sell a third of any coin that rises 3x; (3) if INJ+DOGE grow above 20% of the portfolio, move the excess to BTC.
A15: Trailing exit: after T3, track the coin's highest price; sell the last 40% when it falls the trailing % below that high (expected 2029).
A17: Calendar fallback | B17: Sell %
A18: Mar 2028 | B18: =INDEX('Monthly Schedule'!$M$5:$M$28,MATCH(A18,'Monthly Schedule'!$A$5:$A$28,0)) -> 0.1
A19: Sep 2028 | B19: =INDEX('Monthly Schedule'!$M$5:$M$28,MATCH(A19,'Monthly Schedule'!$A$5:$A$28,0)) -> 0.1
A20: Oct 2028 | B20: =INDEX('Monthly Schedule'!$M$5:$M$28,MATCH(A20,'Monthly Schedule'!$A$5:$A$28,0)) -> 0.15
A21: Nov 2028 | B21: =INDEX('Monthly Schedule'!$M$5:$M$28,MATCH(A21,'Monthly Schedule'!$A$5:$A$28,0)) -> 0.1
A22: Dec 2028 | B22: =INDEX('Monthly Schedule'!$M$5:$M$28,MATCH(A22,'Monthly Schedule'!$A$5:$A$28,0)) -> 0.15
A23: Total by Dec 2028 | B23: =SUM(B18:B22) -> 0.6

Sheet Tracker
A1: Tracker — log every buy and sell
A2: Fill the yellow columns (A–E) on each trade. Quantity, TDS and the summary calculate automatically. Enter today's prices in the summary's yellow column.
A3: Example (format only, not counted):
A4: 01-Jan-2027 | B4: BTC | C4: Buy | D4: 7800000 | E4: 2250 | F4: =E4/D4 -> 0.00028846154 | G4: =IF(C4="Sell",E4*Inputs!$B$10,0) -> 0 | H4: Monthly buy #1
A6: Date | B6: Coin | C6: Buy / Sell | D6: Price per coin (₹) | E6: Amount (₹) | F6: Quantity | G6: TDS (₹) | H6: Note | J6: Coin | K6: Bought qty | L6: Sold qty | M6: Holding qty | N6: Invested (₹) | O6: Avg buy price (₹) | P6: Sold for (₹) | Q6: Today's price (₹) | R6: Value now (₹) | S6: Total P/L (₹) | T6: P/L % | U6: Est. tax on realised gain (₹) | V6: Target 1 (₹) | W6: Next action
F7: =IF(OR(D7="",E7=""),"",IFERROR(E7/D7,0)) | G7: =IF(C7="Sell",E7*Inputs!$B$10,0) -> 0 | J7: BTC | K7: =SUMIFS($F$7:$F$206,$B$7:$B$206,J7,$C$7:$C$206,"Buy") -> 0 | L7: =SUMIFS($F$7:$F$206,$B$7:$B$206,J7,$C$7:$C$206,"Sell") -> 0 | M7: =K7-L7 -> 0 | N7: =SUMIFS($E$7:$E$206,$B$7:$B$206,J7,$C$7:$C$206,"Buy") -> 0 | O7: =IFERROR(N7/K7,0) -> 0 | P7: =SUMIFS($E$7:$E$206,$B$7:$B$206,J7,$C$7:$C$206,"Sell") -> 0 | Q7: =Inputs!E14 -> 7812728 | R7: =M7*Q7 -> 0 | S7: =R7+P7-N7 -> 0 | T7: =IFERROR(S7/N7,0) -> 0 | U7: =MAX(0,P7-L7*O7)*Inputs!$B$9 -> 0 | V7: ='Sell Plan'!D5 -> 10648000 | W7: =IF(M7<=0,"Nothing held",IF(Q7>='Sell Plan'!J5,"Above T3: trailing exit",IF(Q7>='Sell Plan'!G5,"Above T2: sell 20% if not done",IF(Q7>=V7,"Above T1: sell 20% if not done",IF(Q7<='Buy Plan'!I5,"At/below Dip 2 level",IF(Q7<='Buy Plan'!E5,"At/below Dip 1 level","Hold / keep monthly buys")))))) -> Nothing held
F8: =IF(OR(D8="",E8=""),"",IFERROR(E8/D8,0)) | G8: =IF(C8="Sell",E8*Inputs!$B$10,0) -> 0 | J8: ETH | K8: =SUMIFS($F$7:$F$206,$B$7:$B$206,J8,$C$7:$C$206,"Buy") -> 0 | L8: =SUMIFS($F$7:$F$206,$B$7:$B$206,J8,$C$7:$C$206,"Sell") -> 0 | M8: =K8-L8 -> 0 | N8: =SUMIFS($E$7:$E$206,$B$7:$B$206,J8,$C$7:$C$206,"Buy") -> 0 | O8: =IFERROR(N8/K8,0) -> 0 | P8: =SUMIFS($E$7:$E$206,$B$7:$B$206,J8,$C$7:$C$206,"Sell") -> 0 | Q8: =Inputs!E15 -> 234062.4 | R8: =M8*Q8 -> 0 | S8: =R8+P8-N8 -> 0 | T8: =IFERROR(S8/N8,0) -> 0 | U8: =MAX(0,P8-L8*O8)*Inputs!$B$9 -> 0 | V8: ='Sell Plan'!D6 -> 367840 | W8: =IF(M8<=0,"Nothing held",IF(Q8>='Sell Plan'!J6,"Above T3: trailing exit",IF(Q8>='Sell Plan'!G6,"Above T2: sell 20% if not done",IF(Q8>=V8,"Above T1: sell 20% if not done",IF(Q8<='Buy Plan'!I6,"At/below Dip 2 level",IF(Q8<='Buy Plan'!E6,"At/below Dip 1 level","Hold / keep monthly buys")))))) -> Nothing held
F9: =IF(OR(D9="",E9=""),"",IFERROR(E9/D9,0)) | G9: =IF(C9="Sell",E9*Inputs!$B$10,0) -> 0 | J9: SOL | K9: =SUMIFS($F$7:$F$206,$B$7:$B$206,J9,$C$7:$C$206,"Buy") -> 0 | L9: =SUMIFS($F$7:$F$206,$B$7:$B$206,J9,$C$7:$C$206,"Sell") -> 0 | M9: =K9-L9 -> 0 | N9: =SUMIFS($E$7:$E$206,$B$7:$B$206,J9,$C$7:$C$206,"Buy") -> 0 | O9: =IFERROR(N9/K9,0) -> 0 | P9: =SUMIFS($E$7:$E$206,$B$7:$B$206,J9,$C$7:$C$206,"Sell") -> 0 | Q9: =Inputs!E16 -> 10309.2 | R9: =M9*Q9 -> 0 | S9: =R9+P9-N9 -> 0 | T9: =IFERROR(S9/N9,0) -> 0 | U9: =MAX(0,P9-L9*O9)*Inputs!$B$9 -> 0 | V9: ='Sell Plan'!D7 -> 17424 | W9: =IF(M9<=0,"Nothing held",IF(Q9>='Sell Plan'!J7,"Above T3: trailing exit",IF(Q9>='Sell Plan'!G7,"Above T2: sell 20% if not done",IF(Q9>=V9,"Above T1: sell 20% if not done",IF(Q9<='Buy Plan'!I7,"At/below Dip 2 level",IF(Q9<='Buy Plan'!E7,"At/below Dip 1 level","Hold / keep monthly buys")))))) -> Nothing held
F10: =IF(OR(D10="",E10=""),"",IFERROR(E10/D10,0)) | G10: =IF(C10="Sell",E10*Inputs!$B$10,0) -> 0 | J10: BNB | K10: =SUMIFS($F$7:$F$206,$B$7:$B$206,J10,$C$7:$C$206,"Buy") -> 0 | L10: =SUMIFS($F$7:$F$206,$B$7:$B$206,J10,$C$7:$C$206,"Sell") -> 0 | M10: =K10-L10 -> 0 | N10: =SUMIFS($E$7:$E$206,$B$7:$B$206,J10,$C$7:$C$206,"Buy") -> 0 | O10: =IFERROR(N10/K10,0) -> 0 | P10: =SUMIFS($E$7:$E$206,$B$7:$B$206,J10,$C$7:$C$206,"Sell") -> 0 | Q10: =Inputs!E17 -> 69928.32 | R10: =M10*Q10 -> 0 | S10: =R10+P10-N10 -> 0 | T10: =IFERROR(S10/N10,0) -> 0 | U10: =MAX(0,P10-L10*O10)*Inputs!$B$9 -> 0 | V10: ='Sell Plan'!D8 -> 96800 | W10: =IF(M10<=0,"Nothing held",IF(Q10>='Sell Plan'!J8,"Above T3: trailing exit",IF(Q10>='Sell Plan'!G8,"Above T2: sell 20% if not done",IF(Q10>=V10,"Above T1: sell 20% if not done",IF(Q10<='Buy Plan'!I8,"At/below Dip 2 level",IF(Q10<='Buy Plan'!E8,"At/below Dip 1 level","Hold / keep monthly buys")))))) -> Nothing held
F11: =IF(OR(D11="",E11=""),"",IFERROR(E11/D11,0)) | G11: =IF(C11="Sell",E11*Inputs!$B$10,0) -> 0 | J11: TRX | K11: =SUMIFS($F$7:$F$206,$B$7:$B$206,J11,$C$7:$C$206,"Buy") -> 0 | L11: =SUMIFS($F$7:$F$206,$B$7:$B$206,J11,$C$7:$C$206,"Sell") -> 0 | M11: =K11-L11 -> 0 | N11: =SUMIFS($E$7:$E$206,$B$7:$B$206,J11,$C$7:$C$206,"Buy") -> 0 | O11: =IFERROR(N11/K11,0) -> 0 | P11: =SUMIFS($E$7:$E$206,$B$7:$B$206,J11,$C$7:$C$206,"Sell") -> 0 | Q11: =Inputs!E18 -> 32.2344 | R11: =M11*Q11 -> 0 | S11: =R11+P11-N11 -> 0 | T11: =IFERROR(S11/N11,0) -> 0 | U11: =MAX(0,P11-L11*O11)*Inputs!$B$9 -> 0 | V11: ='Sell Plan'!D9 -> 40.656 | W11: =IF(M11<=0,"Nothing held",IF(Q11>='Sell Plan'!J9,"Above T3: trailing exit",IF(Q11>='Sell Plan'!G9,"Above T2: sell 20% if not done",IF(Q11>=V11,"Above T1: sell 20% if not done",IF(Q11<='Buy Plan'!I9,"At/below Dip 2 level",IF(Q11<='Buy Plan'!E9,"At/below Dip 1 level","Hold / keep monthly buys")))))) -> Nothing held
F12: =IF(OR(D12="",E12=""),"",IFERROR(E12/D12,0)) | G12: =IF(C12="Sell",E12*Inputs!$B$10,0) -> 0 | J12: INJ | K12: =SUMIFS($F$7:$F$206,$B$7:$B$206,J12,$C$7:$C$206,"Buy") -> 0 | L12: =SUMIFS($F$7:$F$206,$B$7:$B$206,J12,$C$7:$C$206,"Sell") -> 0 | M12: =K12-L12 -> 0 | N12: =SUMIFS($E$7:$E$206,$B$7:$B$206,J12,$C$7:$C$206,"Buy") -> 0 | O12: =IFERROR(N12/K12,0) -> 0 | P12: =SUMIFS($E$7:$E$206,$B$7:$B$206,J12,$C$7:$C$206,"Sell") -> 0 | Q12: =Inputs!E19 -> 630.3616 | R12: =M12*Q12 -> 0 | S12: =R12+P12-N12 -> 0 | T12: =IFERROR(S12/N12,0) -> 0 | U12: =MAX(0,P12-L12*O12)*Inputs!$B$9 -> 0 | V12: ='Sell Plan'!D10 -> 1452 | W12: =IF(M12<=0,"Nothing held",IF(Q12>='Sell Plan'!J10,"Above T3: trailing exit",IF(Q12>='Sell Plan'!G10,"Above T2: sell 20% if not done",IF(Q12>=V12,"Above T1: sell 20% if not done",IF(Q12<='Buy Plan'!I10,"At/below Dip 2 level",IF(Q12<='Buy Plan'!E10,"At/below Dip 1 level","Hold / keep monthly buys")))))) -> Nothing held
F13: =IF(OR(D13="",E13=""),"",IFERROR(E13/D13,0)) | G13: =IF(C13="Sell",E13*Inputs!$B$10,0) -> 0 | J13: DOGE | K13: =SUMIFS($F$7:$F$206,$B$7:$B$206,J13,$C$7:$C$206,"Buy") -> 0 | L13: =SUMIFS($F$7:$F$206,$B$7:$B$206,J13,$C$7:$C$206,"Sell") -> 0 | M13: =K13-L13 -> 0 | N13: =SUMIFS($E$7:$E$206,$B$7:$B$206,J13,$C$7:$C$206,"Buy") -> 0 | O13: =IFERROR(N13/K13,0) -> 0 | P13: =SUMIFS($E$7:$E$206,$B$7:$B$206,J13,$C$7:$C$206,"Sell") -> 0 | Q13: =Inputs!E20 -> 7.888232 | R13: =M13*Q13 -> 0 | S13: =R13+P13-N13 -> 0 | T13: =IFERROR(S13/N13,0) -> 0 | U13: =MAX(0,P13-L13*O13)*Inputs!$B$9 -> 0 | V13: ='Sell Plan'!D11 -> 17.424 | W13: =IF(M13<=0,"Nothing held",IF(Q13>='Sell Plan'!J11,"Above T3: trailing exit",IF(Q13>='Sell Plan'!G11,"Above T2: sell 20% if not done",IF(Q13>=V13,"Above T1: sell 20% if not done",IF(Q13<='Buy Plan'!I11,"At/below Dip 2 level",IF(Q13<='Buy Plan'!E11,"At/below Dip 1 level","Hold / keep monthly buys")))))) -> Nothing held
F14: =IF(OR(D14="",E14=""),"",IFERROR(E14/D14,0)) | G14: =IF(C14="Sell",E14*Inputs!$B$10,0) -> 0 | J14: Total | N14: =SUM(N7:N13) -> 0 | P14: =SUM(P7:P13) -> 0 | R14: =SUM(R7:R13) -> 0 | S14: =SUM(S7:S13) -> 0 | T14: =IFERROR(S14/N14,0) -> 0 | U14: =SUM(U7:U13) -> 0
F15: =IF(OR(D15="",E15=""),"",IFERROR(E15/D15,0)) | G15: =IF(C15="Sell",E15*Inputs!$B$10,0) -> 0
F16: =IF(OR(D16="",E16=""),"",IFERROR(E16/D16,0)) | G16: =IF(C16="Sell",E16*Inputs!$B$10,0) -> 0 | J16: Tax estimate uses your average buy price (30% + 4% cess on gains; losses not offset). TDS in column G is credited when you file. Confirm with a tax adviser.
F17: =IF(OR(D17="",E17=""),"",IFERROR(E17/D17,0)) | G17: =IF(C17="Sell",E17*Inputs!$B$10,0) -> 0
F18: =IF(OR(D18="",E18=""),"",IFERROR(E18/D18,0)) | G18: =IF(C18="Sell",E18*Inputs!$B$10,0) -> 0
F19: =IF(OR(D19="",E19=""),"",IFERROR(E19/D19,0)) | G19: =IF(C19="Sell",E19*Inputs!$B$10,0) -> 0
F20: =IF(OR(D20="",E20=""),"",IFERROR(E20/D20,0)) | G20: =IF(C20="Sell",E20*Inputs!$B$10,0) -> 0
F21: =IF(OR(D21="",E21=""),"",IFERROR(E21/D21,0)) | G21: =IF(C21="Sell",E21*Inputs!$B$10,0) -> 0
F22: =IF(OR(D22="",E22=""),"",IFERROR(E22/D22,0)) | G22: =IF(C22="Sell",E22*Inputs!$B$10,0) -> 0
F23: =IF(OR(D23="",E23=""),"",IFERROR(E23/D23,0)) | G23: =IF(C23="Sell",E23*Inputs!$B$10,0) -> 0
F24: =IF(OR(D24="",E24=""),"",IFERROR(E24/D24,0)) | G24: =IF(C24="Sell",E24*Inputs!$B$10,0) -> 0
F25: =IF(OR(D25="",E25=""),"",IFERROR(E25/D25,0)) | G25: =IF(C25="Sell",E25*Inputs!$B$10,0) -> 0
F26: =IF(OR(D26="",E26=""),"",IFERROR(E26/D26,0)) | G26: =IF(C26="Sell",E26*Inputs!$B$10,0) -> 0
F27: =IF(OR(D27="",E27=""),"",IFERROR(E27/D27,0)) | G27: =IF(C27="Sell",E27*Inputs!$B$10,0) -> 0
F28: =IF(OR(D28="",E28=""),"",IFERROR(E28/D28,0)) | G28: =IF(C28="Sell",E28*Inputs!$B$10,0) -> 0
... F206: =IF(OR(D206="",E206=""),"",IFERROR(E206/D206,0)) | G206: =IF(C206="Sell",E206*Inputs!$B$10,0) -> 0

Sheet Notes & Risks
A1: Notes, scenarios and risks
A2: Read before using the plan.
A4: How the plan was built
A5: • Based on Binance daily prices for each coin's full history, rolling 2-year returns, and the Bitcoin 4-year cycle (tops Dec 2017, Nov 2021, Oct 2025).
A6: • Today (Oct 2026) sits at the same cycle point as Nov 2018 and Oct 2022; the plan assumes 2027 resembles 2019/2023 and 2028 resembles 2020/2024.
A8: Possible results (rough, before tax)
A9: • Cycle repeats, Targets 1–2 hit in 2028: ₹1 L → about ₹1.6–2.2 L
A10: • Strong rally, all targets hit, SOL/INJ surge: ₹2.5 L or more
A11: • Cycle breaks, prices flat or falling: ₹50,000 – ₹1 L
A13: Indian tax
A14: • 30% tax + 4% cess on every profit; losses cannot reduce tax on gains.
A15: • 1% TDS deducted on every sale; adjusted against your tax when you file.
... A23: • This is a statistical scenario, not financial advice. If in doubt, consult a SEBI-registered adviser.
